wandb_core/__init__.py
wandb_core_alpha-0.0.1a3.data/platlib/wandb_core/bin-darwin-amd64/wandb-nexus
wandb_core_alpha-0.0.1a3.data/platlib/wandb_core/bin-darwin-arm64/wandb-nexus
wandb_core_alpha-0.0.1a3.data/platlib/wandb_core/bin-linux-amd64/wandb-nexus
wandb_core_alpha-0.0.1a3.data/platlib/wandb_core/bin-windows-amd64/wandb-nexus
wandb_core_alpha-0.0.1a3.dist-info/METADATA
wandb_core_alpha-0.0.1a3.dist-info/WHEEL
wandb_core_alpha-0.0.1a3.dist-info/top_level.txt
wandb_core_alpha-0.0.1a3.dist-info/RECORD
