Metadata-Version: 2.1
Name: wandb-core-alpha
Version: 0.0.1a3
Summary: Wandb core
License: MIT license
Requires-Python: >=3.6
